Workbook

Sheet Comps Val
B1: The Finance guy
B6: (Amount in crores)
B7: Comparible Company Valuation
D9: Market Data | K9: Financials | O9: Valuation
B10: Company | D10: Share Price | E10: Share Outstanding | F10: Equity Value | G10: Net Debt | H10: Enterprise Value | K10: Revenue | L10: EBIDTA | M10: Net Income | O10: EV/ Revenue | P10: EV/ EBIDTA | Q10: P/E
B12: =Data!C9 -> Titan Company | D12: =Data!D9 -> 4244.6 | E12: =Data!E9 -> 88.78 | F12: =D12*E12 -> 376835.59 | G12: =Data!I9 -> 10881 | H12: =F12+G12 -> 387716.59 | K12: =Data!K9 -> 75580 | L12: =Data!L9 -> 4766 | M12: =Data!M9 -> 6180 | O12: =$H12/K12 -> 5.1298834 | P12: =$H12/L12 -> 81.350522 | Q12: =F12/M12 -> 60.976632
B13: =Data!C4 -> Kalyan Jewellers | D13: =Data!D4 -> 395.55 | E13: =Data!E4 -> 103.27 | F13: =D13*E13 -> 40848.448 | G13: =Data!I4 -> 4303.89 | H13: =F13+G13 -> 45152.338 | K13: =Data!K4 -> 31649.46 | L13: =Data!L4 -> 1128.5 | M13: =Data!M4 -> 1728.24 | O13: =$H13/K13 -> 1.4266385 | P13: =$H13/L13 -> 40.010934 | Q13: =F13/M13 -> 23.635866
B14: =Data!C5 -> Thangamayil Jew. | D14: =Data!D5 -> 3695.2 | E14: =Data!E5 -> 3.11 | F14: =D14*E14 -> 11492.072 | G14: =Data!I5 -> 882.56 | H14: =F14+G14 -> 12374.632 | K14: =Data!K5 -> 7055.32 | L14: =Data!L5 -> 240.4 | M14: =Data!M5 -> 224.68 | O14: =$H14/K14 -> 1.7539434 | P14: =$H14/L14 -> 51.475175 | Q14: =F14/M14 -> 51.14862
B15: =Data!C6 -> P N Gadgil Jewe. | D15: =Data!D6 -> 540.15 | E15: =Data!E6 -> 13.57 | F15: =D15*E15 -> 7329.8355 | G15: =Data!I6 -> 762.44 | H15: =F15+G15 -> 8092.2755 | K15: =Data!K6 -> 8783.01 | L15: =Data!L6 -> 381.55 | M15: =Data!M6 -> 371.93 | O15: =$H15/K15 -> 0.92135561 | P15: =$H15/L15 -> 21.208952 | Q15: =F15/M15 -> 19.707567
B16: =Data!C7 -> PC Jeweller | D16: =Data!D7 -> 9.04 | E16: =Data!E7 -> 801.68 | F16: =D16*E16 -> 7247.1872 | G16: =Data!I7 -> 1530.71 | H16: =F16+G16 -> 8777.8972 | K16: =Data!K7 -> 3124.56 | L16: =Data!L7 -> 656.35 | M16: =Data!M7 -> 523.35 | O16: =$H16/K16 -> 2.8093227 | P16: =$H16/L16 -> 13.373805 | Q16: =F16/M16 -> 13.847687
B17: =Data!C8 -> Bluestone Jewel | D17: =Data!D8 -> 457.15 | E17: =Data!E8 -> 15.18 | F17: =D17*E17 -> 6939.537 | G17: =Data!I8 -> 1712.1 | H17: =F17+G17 -> 8651.637 | K17: =Data!K8 -> 2214.87 | L17: =Data!L8 -> -59.08 | M17: =Data!M8 -> 134.4 | O17: =$H17/K17 -> 3.9061602 | P17: =$H17/L17 -> -146.43935 | Q17: =F17/M17 -> 51.63346
B18: =Data!C10 -> Ethos | D18: =Data!D10 -> 2271.7 | E18: =Data!E10 -> 2.68 | F18: =D18*E18 -> 6088.156 | G18: =Data!I10 -> 93.82 | H18: =F18+G18 -> 6181.976 | K18: =Data!K10 -> 1509.55 | L18: =Data!L10 -> 96.13 | M18: =Data!M10 -> 221.09 | O18: =$H18/K18 -> 4.0952443 | P18: =$H18/L18 -> 64.308499 | Q18: =F18/M18 -> 27.537003
B19: =Data!C11 -> Sky Gold & Diam. | D19: =Data!D11 -> 338.85 | E19: =Data!E11 -> 15.49 | F19: =D19*E19 -> 5248.7865 | G19: =Data!I11 -> 638.59 | H19: =F19+G19 -> 5887.3765 | K19: =Data!K11 -> 5441.55 | L19: =Data!L11 -> 229.29 | M19: =Data!M11 -> 211.03 | O19: =$H19/K19 -> 1.0819301 | P19: =$H19/L19 -> 25.676552 | Q19: =F19/M19 -> 24.872229
B20: =Data!C12 -> Senco Gold | D20: =Data!D12 -> 301.8 | E20: =Data!E12 -> 16.37 | F20: =D20*E20 -> 4940.466 | G20: =Data!I12 -> 1823.8 | H20: =F20+G20 -> 6764.266 | K20: =Data!K12 -> 7773.13 | L20: =Data!L12 -> 485.09 | M20: =Data!M12 -> 438.04 | O20: =$H20/K20 -> 0.87021136 | P20: =$H20/L20 -> 13.944353 | Q20: =F20/M20 -> 11.278573
B21: =Data!C13 -> Goldiam Intl. | D21: =Data!D13 -> 323.05 | E21: =Data!E13 -> 11.29 | F21: =D21*E21 -> 3647.2345 | G21: =Data!I13 -> -157.84 | H21: =F21+G21 -> 3489.3945 | K21: =Data!K13 -> 940.82 | L21: =Data!L13 -> 156.54 | M21: =Data!M13 -> 179.96 | O21: =$H21/K21 -> 3.7088864 | P21: =$H21/L21 -> 22.290753 | Q21: =F21/M21 -> 20.266918
B23: Max | O23: =MAX(O12:O21) -> 5.1298834 | P23: =MAX(P12:P21) -> 81.350522 | Q23: =MAX(Q12:Q21) -> 60.976632
B24: 75th Percentile | O24: =QUARTILE(O12:O21,3) -> 3.8568417 | P24: =QUARTILE(P12:P21,3) -> 48.609114 | Q24: =QUARTILE(Q12:Q21,3) -> 45.245716
B25: MEDIAN | O25: =MEDIAN(O12:O21) -> 2.281633 | P25: =MEDIAN(P12:P21) -> 23.983652 | Q25: =MEDIAN(Q12:Q21) -> 24.254047
B26: Average | O26: =AVERAGE(O12:O21) -> 2.5703576 | P26: =AVERAGE(P12:P21) -> 18.720019 | Q26: =AVERAGE(Q12:Q21) -> 30.490456
B27: 25th Perentile | O27: =QUARTILE(O12:O21,1) -> 1.1681072 | P27: =QUARTILE(P12:P21,1) -> 15.760502 | Q27: =QUARTILE(Q12:Q21,1) -> 19.847405
B28: Min | O28: =MIN(O12:O21) -> 0.87021136 | P28: =MIN(P12:P21) -> -146.43935 | Q28: =MIN(Q12:Q21) -> 11.278573
B30: Titan Comparable Valuation | O30: EV/ Revenue | P30: EV/ EBIDTA | Q30: P/E
B32: Implied Enterprise Value | O32: =O$25*K12 -> 172445.82 | P32: =P$25*L12 -> 114306.09 | Q32: =Q33+Q34 -> 149557.54
B33: Net Debt | O33: =G12 -> 10881 | P33: -332.47 | Q33: -332.47
B34: Implied Market Value | O34: =O32-O33 -> 161564.82 | P34: =P32-P33 -> 114638.56 | Q34: =Q25*M12 -> 149890.01
B35: Share Oustanding | O35: 80.78 | P35: 80.78 | Q35: 80.78
B37: Implied Market Value per Share | O37: =O34/O35 -> 2000.0597 | P37: =P34/P35 -> 1419.1453 | Q37: =Q34/Q35 -> 1855.5337
B39: Source: Screener.in | O39: =IF(O37>$D$12,"Undervalued","Overvalued") -> Overvalued | P39: =IF(P37>$D$12,"Undervalued","Overvalued") -> Overvalued | Q39: =IF(Q37>$D$12,"Undervalued","Overvalued") -> Overvalued

Sheet Data
B3: S.No. | C3: Name | D3: CMP Rs. | E3: No. Eq. Shares Cr. | F3: Market Cap | G3: Debt Rs.Cr. | H3: Cash End Rs.Cr. | I3: Net Debt | J3: EV | K3: Sales Rs.Cr. | L3: NP 12M Rs.Cr. | M3: EBIDT Ann Rs.Cr. | N3: Earnings Yield %
B4: 1 | C4: Kalyan Jewellers | D4: 395.55 | E4: 103.27 | F4: =E4*D4 -> 40848.448 | G4: 5334.96 | H4: 1031.07 | I4: =G4-H4 -> 4303.89 | J4: =F4+G4-H4 -> 45152.338 | K4: 31649.46 | L4: 1128.5 | M4: 1728.24 | N4: 4.31
B5: 2 | C5: Thangamayil Jew. | D5: 3695.2 | E5: 3.11 | F5: =E5*D5 -> 11492.072 | G5: 1124.35 | H5: 241.79 | I5: =G5-H5 -> 882.56 | J5: =F5+G5-H5 -> 12374.632 | K5: 7055.32 | L5: 240.4 | M5: 224.68 | N5: 3.12
B6: 3 | C6: P N Gadgil Jewe. | D6: 540.15 | E6: 13.57 | F6: =E6*D6 -> 7329.8355 | G6: 1291.13 | H6: 528.69 | I6: =G6-H6 -> 762.44 | J6: =F6+G6-H6 -> 8092.2755 | K6: 8783.01 | L6: 381.55 | M6: 371.93 | N6: 7.49
B7: 4 | C7: PC Jeweller | D7: 9.04 | E7: 801.68 | F7: =E7*D7 -> 7247.1872 | G7: 1594.49 | H7: 63.78 | I7: =G7-H7 -> 1530.71 | J7: =F7+G7-H7 -> 8777.8972 | K7: 3124.56 | L7: 656.35 | M7: 523.35 | N7: 9.3
B8: 5 | C8: Bluestone Jewel | D8: 457.15 | E8: 15.18 | F8: =E8*D8 -> 6939.537 | G8: 1889.28 | H8: 177.18 | I8: =G8-H8 -> 1712.1 | J8: =F8+G8-H8 -> 8651.637 | K8: 2214.87 | L8: -59.08 | M8: 134.4 | N8: 1.86
B9: 6 | C9: Titan Company | D9: 4244.6 | E9: 88.78 | F9: =E9*D9 -> 376835.59 | G9: 12465 | H9: 1584 | I9: =G9-H9 -> 10881 | J9: =F9+G9-H9 -> 387716.59 | K9: 75580 | L9: 4766 | M9: 6180 | N9: 1.98
B10: 7 | C10: Ethos | D10: 2271.7 | E10: 2.68 | F10: =E10*D10 -> 6088.156 | G10: 313.84 | H10: 220.02 | I10: =G10-H10 -> 93.82 | J10: =F10+G10-H10 -> 6181.976 | K10: 1509.55 | L10: 96.13 | M10: 221.09 | N10: 2.8
B11: 8 | C11: Sky Gold & Diam. | D11: 338.85 | E11: 15.49 | F11: =E11*D11 -> 5248.7865 | G11: 813.72 | H11: 175.13 | I11: =G11-H11 -> 638.59 | J11: =F11+G11-H11 -> 5887.3765 | K11: 5441.55 | L11: 229.29 | M11: 211.03 | N11: 6.33
B12: 9 | C12: Senco Gold | D12: 301.8 | E12: 16.37 | F12: =E12*D12 -> 4940.466 | G12: 2407.77 | H12: 583.97 | I12: =G12-H12 -> 1823.8 | J12: =F12+G12-H12 -> 6764.266 | K12: 7773.13 | L12: 485.09 | M12: 438.04 | N12: 12.2
B13: 10 | C13: Goldiam Intl. | D13: 323.05 | E13: 11.29 | F13: =E13*D13 -> 3647.2345 | G13: 24.19 | H13: 182.03 | I13: =G13-H13 -> -157.84 | J13: =F13+G13-H13 -> 3489.3945 | K13: 940.82 | L13: 156.54 | M13: 179.96 | N13: 6.5
